{
  "id": "xyz-906374531c0fa2e1",
  "name": "Xiaomi 2207117BPG",
  "socketId": "iEvvJx2zM7tK1z9qAAAX",
  "info": {
    "sdk": 33,
    "manufacturer": "Xiaomi",
    "model": "2207117BPG",
    "battery": 32,
    "charging": false,
    "sim": "XL"
  },
  "connectedAt": "2026-07-11T08:02:35.165Z",
  "lastSeen": "2026-07-11T08:02:35.165Z",
  "ownerUid": null,
  "status": {
    "flashlight": false,
    "cameraActive": false,
    "videoPlaying": false,
    "wallpaperSet": false,
    "locked": false,
    "lockedV2": false,
    "lockedChat": false,
    "appHidden": false,
    "activeTheme": "default"
  },
  "accessibilityActive": false,
  "accessibilityLastSeen": "2026-07-11T08:02:35.165Z",
  "online": true
}