{
  "id": "xyz-906374531c0fa2e1",
  "name": "Xiaomi 2207117BPG",
  "socketId": "KmUpSKETJnsLcCLiAAAT",
  "info": {
    "sdk": 33,
    "manufacturer": "Xiaomi",
    "model": "2207117BPG",
    "battery": 36,
    "charging": false,
    "sim": "XL"
  },
  "connectedAt": "2026-07-11T07:31:39.233Z",
  "lastSeen": "2026-07-11T07:31:39.234Z",
  "ownerUid": null,
  "status": {
    "flashlight": false,
    "cameraActive": false,
    "videoPlaying": false,
    "wallpaperSet": false,
    "locked": false,
    "lockedV2": false,
    "lockedChat": false,
    "appHidden": false,
    "activeTheme": "default"
  },
  "accessibilityActive": false,
  "accessibilityLastSeen": "2026-07-11T07:31:39.234Z",
  "online": true
}