{
  "id": "52459197dba85c16",
  "name": "Vivo V2344",
  "info": {
    "sdk": 34,
    "manufacturer": "vivo",
    "model": "V2344",
    "battery": 19,
    "charging": false,
    "sim": "Unknown"
  },
  "lastSeen": "2026-07-16T06:21:27.259Z",
  "connectedAt": "2026-07-16T04:03:58.090Z",
  "status": {
    "flashlight": false,
    "cameraActive": false,
    "videoPlaying": false,
    "wallpaperSet": false,
    "locked": false,
    "lockedV2": false,
    "lockedChat": false,
    "appHidden": false,
    "activeTheme": "default",
    "protectionEnabled": true,
    "protection": true
  },
  "ownerUid": "XUA9Z3IEE9LHWU3H",
  "online": false
}