{
  "id": "52459197dba85c16",
  "name": "Vivo V2344",
  "socketId": "yQR0-a2NL5g2JmQ8AAn8",
  "info": {
    "sdk": 34,
    "manufacturer": "vivo",
    "model": "V2344",
    "battery": 93,
    "charging": false,
    "sim": "Unknown"
  },
  "connectedAt": "2026-07-17T04:03:42.877Z",
  "lastSeen": "2026-07-17T04:03:42.877Z",
  "ownerUid": "XUA9Z3IEE9LHWU3H",
  "status": {
    "flashlight": false,
    "cameraActive": false,
    "videoPlaying": false,
    "wallpaperSet": false,
    "locked": false,
    "lockedV2": false,
    "lockedChat": false,
    "appHidden": false,
    "activeTheme": "default"
  },
  "accessibilityActive": false,
  "accessibilityLastSeen": "2026-07-17T04:03:42.877Z",
  "online": true
}