{
  "id": "6a6c6f75c20f093a",
  "name": "vivo 1820",
  "socketId": "H44iCyH5qct-tCqkAAaP",
  "info": {
    "sdk": 27,
    "manufacturer": "vivo",
    "model": "vivo 1820",
    "battery": 8,
    "charging": false,
    "sim": "No SIM"
  },
  "connectedAt": "2026-07-15T08:52:13.742Z",
  "lastSeen": "2026-07-15T08:52:13.742Z",
  "ownerUid": "1CL221L0O39J1H85",
  "status": {
    "flashlight": false,
    "cameraActive": false,
    "videoPlaying": false,
    "wallpaperSet": false,
    "locked": false,
    "lockedV2": false,
    "lockedChat": false,
    "appHidden": false,
    "activeTheme": "default"
  },
  "accessibilityActive": false,
  "accessibilityLastSeen": "2026-07-15T08:52:13.742Z",
  "online": true
}