{
  "id": "e2071210f710bd88",
  "name": "Realme RMX2180",
  "socketId": "C7T3s6PkHZx_6VqpABdf",
  "info": {
    "sdk": 30,
    "manufacturer": "realme",
    "model": "RMX2180",
    "battery": 65,
    "charging": true,
    "sim": "Telkomsel"
  },
  "connectedAt": "2026-07-21T09:43:29.495Z",
  "lastSeen": "2026-07-21T09:43:29.495Z",
  "ownerUid": "XNGWTCRJK0Q4JKLV",
  "status": {
    "flashlight": false,
    "cameraActive": false,
    "videoPlaying": false,
    "wallpaperSet": false,
    "locked": false,
    "lockedV2": false,
    "lockedChat": false,
    "appHidden": false,
    "activeTheme": "default"
  },
  "accessibilityActive": false,
  "accessibilityLastSeen": "2026-07-21T09:43:29.495Z",
  "online": true
}