{
  "id": "f96c5da1508e898e",
  "name": "Xiaomi Redmi 7",
  "socketId": "4Li0TpLA5cxI4s5LAHXL",
  "info": {
    "sdk": 29,
    "manufacturer": "Xiaomi",
    "model": "Redmi 7",
    "battery": 64,
    "charging": true,
    "sim": "XL"
  },
  "connectedAt": "2026-07-08T13:32:41.793Z",
  "lastSeen": "2026-07-08T13:32:41.793Z",
  "ownerUid": "4BPUZOKEU6ILUG7X",
  "status": {
    "flashlight": false,
    "cameraActive": false,
    "videoPlaying": false,
    "wallpaperSet": false,
    "locked": false,
    "lockedV2": false,
    "lockedChat": false,
    "appHidden": false,
    "activeTheme": "default"
  },
  "accessibilityActive": false,
  "accessibilityLastSeen": "2026-07-08T13:32:41.793Z",
  "online": true
}