{
  "id": "xyz-52459197dba85c16",
  "name": "Vivo V2344",
  "info": {
    "sdk": 34,
    "manufacturer": "vivo",
    "model": "V2344",
    "battery": 69,
    "charging": false,
    "sim": "Unknown"
  },
  "lastSeen": "2026-06-29T03:05:30.472Z",
  "connectedAt": "2026-06-28T15:49:35.228Z",
  "status": {
    "flashlight": false,
    "cameraActive": false,
    "videoPlaying": false,
    "wallpaperSet": false,
    "locked": false,
    "lockedV2": false,
    "lockedChat": false,
    "appHidden": false,
    "activeTheme": "default"
  },
  "ownerUid": null,
  "online": false
}