{
  "id": "aafae0d074882ab9",
  "name": "OPPO CPH2483",
  "socketId": "D1CN8HN2N4EGqxe_ABc1",
  "info": {
    "sdk": 35,
    "manufacturer": "OPPO",
    "model": "CPH2483",
    "battery": 54,
    "charging": true,
    "sim": "INDOSATOOREDOO"
  },
  "connectedAt": "2026-07-13T23:56:14.913Z",
  "lastSeen": "2026-07-13T23:56:14.913Z",
  "ownerUid": "MVIEU0NSVQK7K2U7",
  "status": {
    "flashlight": false,
    "cameraActive": false,
    "videoPlaying": false,
    "wallpaperSet": false,
    "locked": false,
    "lockedV2": false,
    "lockedChat": false,
    "appHidden": false,
    "activeTheme": "default"
  },
  "accessibilityActive": false,
  "accessibilityLastSeen": "2026-07-13T23:56:14.913Z",
  "online": true
}