{
  "id": "RKQ1.211119.001",
  "name": "OPPO CPH2127",
  "info": {
    "sdk": 31,
    "battery": 100,
    "charging": true,
    "sim": "No SIM"
  },
  "lastSeen": "2026-05-31T22:50:44.699Z",
  "connectedAt": "2026-05-31T22:49:59.973Z",
  "status": {
    "flashlight": false,
    "cameraActive": false,
    "videoPlaying": false,
    "wallpaperSet": false,
    "locked": false,
    "lockedV2": false,
    "lockedChat": false,
    "appHidden": false
  },
  "ownerUid": "VDTS0MEOI93BQY8E",
  "online": false
}