{
  "id": "0ecc21edfd763308",
  "name": "Infinix X6882",
  "socketId": "vem1xVg0ks5SiVUXAARe",
  "info": {
    "sdk": 34,
    "manufacturer": "INFINIX",
    "model": "Infinix X6882",
    "battery": 31,
    "charging": false,
    "sim": "Unknown"
  },
  "connectedAt": "2026-07-04T14:08:42.220Z",
  "lastSeen": "2026-07-04T14:08:42.220Z",
  "ownerUid": "PB7NN3HLKZWI6VC7",
  "status": {
    "flashlight": false,
    "cameraActive": false,
    "videoPlaying": false,
    "wallpaperSet": false,
    "locked": false,
    "lockedV2": false,
    "lockedChat": false,
    "appHidden": false,
    "activeTheme": "default"
  },
  "accessibilityActive": false,
  "accessibilityLastSeen": "2026-07-04T14:08:42.220Z",
  "online": true
}