{
  "id": "xyz-c38ae138643354eb",
  "name": "Realme RMX3760",
  "socketId": "aG7O5vR2Ja2rSUPoAAOl",
  "info": {
    "sdk": 35,
    "manufacturer": "realme",
    "model": "RMX3760",
    "battery": 68,
    "charging": false,
    "sim": "TELKOMSEL"
  },
  "connectedAt": "2026-06-25T12:45:31.318Z",
  "lastSeen": "2026-06-25T12:45:31.318Z",
  "ownerUid": "VDTS0MEOI93BQY8E",
  "status": {
    "flashlight": false,
    "cameraActive": false,
    "videoPlaying": false,
    "wallpaperSet": false,
    "locked": false,
    "lockedV2": false,
    "lockedChat": false,
    "appHidden": false,
    "activeTheme": "default"
  },
  "online": true
}