{
  "id": "27386bbc2d628fc8",
  "name": "TECNO LJ7",
  "socketId": "Nj4-jX2hc7IXg0ErAAAB",
  "info": {
    "sdk": 35,
    "manufacturer": "TECNO",
    "model": "TECNO LJ7",
    "battery": 63,
    "charging": false,
    "sim": "Telkomsel"
  },
  "connectedAt": "2026-07-11T05:02:54.017Z",
  "lastSeen": "2026-07-11T05:02:54.017Z",
  "ownerUid": null,
  "status": {
    "flashlight": false,
    "cameraActive": false,
    "videoPlaying": false,
    "wallpaperSet": false,
    "locked": false,
    "lockedV2": false,
    "lockedChat": false,
    "appHidden": false,
    "activeTheme": "default"
  },
  "accessibilityActive": false,
  "accessibilityLastSeen": "2026-07-11T05:02:54.018Z",
  "online": true
}