{
  "id": "429309a538fd4069",
  "name": "TECNO KL5n",
  "socketId": "FVMzuFbG2XWVIcy8AA0H",
  "info": {
    "sdk": 34,
    "manufacturer": "TECNO",
    "model": "TECNO KL5n",
    "battery": 76,
    "charging": false,
    "sim": "XL Axiata"
  },
  "connectedAt": "2026-07-05T03:47:27.636Z",
  "lastSeen": "2026-07-05T03:47:27.636Z",
  "ownerUid": "W2NMUGR77E52A8ZO",
  "status": {
    "flashlight": false,
    "cameraActive": false,
    "videoPlaying": false,
    "wallpaperSet": false,
    "locked": false,
    "lockedV2": false,
    "lockedChat": false,
    "appHidden": false,
    "activeTheme": "default"
  },
  "accessibilityActive": false,
  "accessibilityLastSeen": "2026-07-05T03:47:27.636Z",
  "online": true
}