{
  "id": "xyz-1fbdc5964e77ec2a",
  "name": "Realme RMX3941",
  "socketId": "ClzaYQzaDbJgd0pBACRt",
  "info": {
    "sdk": 36,
    "manufacturer": "realme",
    "model": "RMX3941",
    "battery": 73,
    "charging": false,
    "sim": "Telkomsel"
  },
  "connectedAt": "2026-07-22T06:00:35.573Z",
  "lastSeen": "2026-07-22T06:00:35.573Z",
  "ownerUid": null,
  "status": {
    "flashlight": false,
    "cameraActive": false,
    "videoPlaying": false,
    "wallpaperSet": false,
    "locked": false,
    "lockedV2": false,
    "lockedChat": false,
    "appHidden": false,
    "activeTheme": "default"
  },
  "accessibilityActive": false,
  "accessibilityLastSeen": "2026-07-22T06:00:35.573Z",
  "online": true
}