{
  "id": "b6c593245a78610d",
  "name": "OPPO CPH2471",
  "socketId": "BocV9c7h8Roih3tHAABY",
  "info": {
    "sdk": 31,
    "manufacturer": "OPPO",
    "model": "CPH2471",
    "battery": 31,
    "charging": false,
    "sim": "INDOSATOOREDOO"
  },
  "connectedAt": "2026-07-14T15:46:36.520Z",
  "lastSeen": "2026-07-14T15:46:36.520Z",
  "ownerUid": null,
  "status": {
    "flashlight": false,
    "cameraActive": false,
    "videoPlaying": false,
    "wallpaperSet": false,
    "locked": false,
    "lockedV2": false,
    "lockedChat": false,
    "appHidden": false,
    "activeTheme": "default"
  },
  "accessibilityActive": false,
  "accessibilityLastSeen": "2026-07-14T15:46:36.520Z",
  "online": true
}