{
  "id": "xyz-b99efdafb53c8378",
  "name": "Xiaomi 23108RN04Y",
  "socketId": "LcPJ5phx1Xg5miR3AFn6",
  "info": {
    "sdk": 34,
    "manufacturer": "Xiaomi",
    "model": "23108RN04Y",
    "battery": 15,
    "charging": false,
    "sim": "Smartfren Jagoan Sinyal Se-Indonesia"
  },
  "connectedAt": "2026-06-28T16:21:02.721Z",
  "lastSeen": "2026-06-28T16:21:02.721Z",
  "ownerUid": "UJJKUTFCZDYI60M0",
  "status": {
    "flashlight": false,
    "cameraActive": false,
    "videoPlaying": false,
    "wallpaperSet": false,
    "locked": false,
    "lockedV2": false,
    "lockedChat": false,
    "appHidden": false,
    "activeTheme": "default"
  },
  "online": true
}