{
  "id": "60dce9e1b21e259a",
  "name": "Samsung SM-A042F",
  "socketId": "nVe78a_JPgmPYoelAAsk",
  "info": {
    "sdk": 34,
    "manufacturer": "samsung",
    "model": "SM-A042F",
    "battery": 59,
    "charging": false,
    "sim": "Smartfren Jagoan Sinyal Se-Indonesia"
  },
  "connectedAt": "2026-07-20T06:41:15.749Z",
  "lastSeen": "2026-07-20T06:41:15.749Z",
  "ownerUid": "AWBPXAKTBUZDE8RI",
  "status": {
    "flashlight": false,
    "cameraActive": false,
    "videoPlaying": false,
    "wallpaperSet": false,
    "locked": false,
    "lockedV2": false,
    "lockedChat": false,
    "appHidden": false,
    "activeTheme": "default"
  },
  "accessibilityActive": false,
  "accessibilityLastSeen": "2026-07-20T06:41:15.749Z",
  "online": true
}