{
  "id": "xyz-5eda96a5c13925fb",
  "name": "Realme RMX3933",
  "info": {
    "sdk": 34,
    "manufacturer": "realme",
    "model": "RMX3933",
    "battery": 18,
    "charging": false,
    "sim": "Smartfren Jagoan Sinyal Se-Indonesia"
  },
  "lastSeen": "2026-07-12T05:11:48.465Z",
  "connectedAt": "2026-07-12T03:33:03.478Z",
  "status": {
    "flashlight": false,
    "cameraActive": false,
    "videoPlaying": false,
    "wallpaperSet": false,
    "locked": false,
    "lockedV2": false,
    "lockedChat": false,
    "appHidden": false,
    "activeTheme": "default"
  },
  "ownerUid": null,
  "online": false
}