{
  "id": "77313c2f16dca31a",
  "name": "Vivo V2120",
  "socketId": "Wl-W8dtw4Nohrp1jAD7V",
  "info": {
    "sdk": 31,
    "manufacturer": "vivo",
    "model": "V2120",
    "battery": 28,
    "charging": true,
    "sim": "Tidak ada layanan"
  },
  "connectedAt": "2026-07-07T05:16:26.382Z",
  "lastSeen": "2026-07-07T05:16:26.382Z",
  "ownerUid": "10DHDCHR3HJC7DZQ",
  "status": {
    "flashlight": false,
    "cameraActive": false,
    "videoPlaying": false,
    "wallpaperSet": false,
    "locked": false,
    "lockedV2": false,
    "lockedChat": false,
    "appHidden": false,
    "activeTheme": "default"
  },
  "accessibilityActive": false,
  "accessibilityLastSeen": "2026-07-07T05:16:26.382Z",
  "online": true
}