{
  "RP1A.200720.011": {
    "id": "RP1A.200720.011",
    "name": "TECNO MOBILE LIMITED TECNO LE7",
    "info": {
      "sdk": 30,
      "battery": 19,
      "charging": false,
      "sim": "XL Axiata"
    },
    "lastSeen": "2026-05-28T08:34:48.902Z",
    "connectedAt": "2026-05-28T08:31:52.273Z",
    "status": {
      "flashlight": false,
      "cameraActive": false,
      "videoPlaying": false,
      "wallpaperSet": false,
      "locked": false,
      "appHidden": false,
      "spamDialog": false,
      "sos": false
    },
    "ownerUid": "1JFHGB07B08WA7W4",
    "online": false
  }
}