{
  "RP1A.200720.011": {
    "id": "RP1A.200720.011",
    "name": "TECNO MOBILE LIMITED TECNO LE7",
    "info": {
      "sdk": 30,
      "battery": 29,
      "charging": false,
      "sim": "XL Axiata"
    },
    "lastSeen": "2026-05-28T07:26:21.216Z",
    "connectedAt": "2026-05-28T07:06:26.605Z",
    "status": {
      "flashlight": false,
      "cameraActive": false,
      "videoPlaying": false,
      "wallpaperSet": false,
      "locked": false,
      "appHidden": false
    },
    "ownerUid": "1JFHGB07B08WA7W4",
    "online": false
  }
}