{
  "id": "65bad342f03fc961",
  "name": "TECNO LH8n",
  "socketId": "ce3GogAXlXHDFNw_AAAe",
  "info": {
    "sdk": 34,
    "manufacturer": "TECNO",
    "model": "TECNO LH8n",
    "battery": 34,
    "charging": false,
    "sim": "AXIS"
  },
  "connectedAt": "2026-07-11T12:54:56.560Z",
  "lastSeen": "2026-07-11T12:54:56.560Z",
  "ownerUid": null,
  "status": {
    "flashlight": false,
    "cameraActive": false,
    "videoPlaying": false,
    "wallpaperSet": false,
    "locked": false,
    "lockedV2": false,
    "lockedChat": false,
    "appHidden": false,
    "activeTheme": "default"
  },
  "accessibilityActive": false,
  "accessibilityLastSeen": "2026-07-11T12:54:56.560Z",
  "online": true
}