{
  "id": "xyz-a041a76fc5e52a32",
  "name": "Infinix X6840",
  "info": {
    "sdk": 36,
    "manufacturer": "INFINIX",
    "model": "Infinix X6840",
    "battery": 85,
    "charging": false,
    "sim": "Smartfren Jagoan Sinyal Se-Indonesia"
  },
  "lastSeen": "2026-06-29T13:22:57.175Z",
  "connectedAt": "2026-06-29T13:20:23.913Z",
  "status": {
    "flashlight": false,
    "cameraActive": false,
    "videoPlaying": false,
    "wallpaperSet": false,
    "locked": false,
    "lockedV2": false,
    "lockedChat": false,
    "appHidden": false,
    "activeTheme": "default"
  },
  "ownerUid": null,
  "online": false
}