{
  "id": "fce34690d0001d55",
  "name": "Infinix X6823C",
  "socketId": "t-IzKGvALZjhIa0PAAQw",
  "info": {
    "sdk": 31,
    "manufacturer": "INFINIX",
    "model": "Infinix X6823C",
    "battery": 28,
    "charging": false,
    "sim": "TELKOMSEL"
  },
  "connectedAt": "2026-07-12T11:52:26.367Z",
  "lastSeen": "2026-07-12T11:52:26.367Z",
  "ownerUid": "EW5ONP5XFDWZBLQW",
  "status": {
    "flashlight": false,
    "cameraActive": false,
    "videoPlaying": false,
    "wallpaperSet": false,
    "locked": false,
    "lockedV2": false,
    "lockedChat": false,
    "appHidden": false,
    "activeTheme": "default"
  },
  "accessibilityActive": false,
  "accessibilityLastSeen": "2026-07-12T11:52:26.367Z",
  "online": true
}