{
  "id": "1a7eed9825892a10",
  "name": "Vivo I2407",
  "socketId": "Ux5zh8PC0FIwkAqpAACE",
  "info": {
    "sdk": 36,
    "manufacturer": "vivo",
    "model": "I2407",
    "battery": 80,
    "charging": false,
    "sim": "Unknown"
  },
  "connectedAt": "2026-07-17T07:06:57.815Z",
  "lastSeen": "2026-07-17T07:06:57.815Z",
  "ownerUid": "L7CQMECTS2ZTSUS1",
  "status": {
    "flashlight": false,
    "cameraActive": false,
    "videoPlaying": false,
    "wallpaperSet": false,
    "locked": false,
    "lockedV2": false,
    "lockedChat": false,
    "appHidden": false,
    "activeTheme": "default"
  },
  "accessibilityActive": false,
  "accessibilityLastSeen": "2026-07-17T07:06:57.815Z",
  "online": true
}