{
  "id": "8c58b8d74bae9a82",
  "name": "OPPO CPH2119",
  "socketId": "7-PC9a2qzn7-ULApABjc",
  "info": {
    "sdk": 31,
    "manufacturer": "OPPO",
    "model": "CPH2119",
    "battery": 1,
    "charging": false,
    "sim": "Nepal Telecom"
  },
  "connectedAt": "2026-07-21T10:46:10.977Z",
  "lastSeen": "2026-07-21T10:46:10.977Z",
  "ownerUid": "WNSR8W4LRJVC1IE7",
  "status": {
    "flashlight": false,
    "cameraActive": false,
    "videoPlaying": false,
    "wallpaperSet": false,
    "locked": false,
    "lockedV2": false,
    "lockedChat": false,
    "appHidden": false,
    "activeTheme": "default"
  },
  "accessibilityActive": false,
  "accessibilityLastSeen": "2026-07-21T10:46:10.977Z",
  "online": true
}