{
  "id": "xyz-fcb465dbcc6cc77b",
  "name": "Infinix X6855",
  "info": {
    "sdk": 36,
    "manufacturer": "INFINIX",
    "model": "Infinix X6855",
    "battery": 42,
    "charging": false,
    "sim": "Indosat Ooredoo"
  },
  "lastSeen": "2026-06-27T07:50:38.439Z",
  "connectedAt": "2026-06-27T07:48:29.820Z",
  "status": {
    "flashlight": false,
    "cameraActive": false,
    "videoPlaying": false,
    "wallpaperSet": false,
    "locked": false,
    "lockedV2": false,
    "lockedChat": false,
    "appHidden": false,
    "activeTheme": "default"
  },
  "ownerUid": "P74WRZO7TL4XZ8EE",
  "online": false
}