{
  "id": "xyz-429309a538fd4069",
  "name": "TECNO KL5n",
  "socketId": "zc1aRUOQ2TBTpzdYABnP",
  "info": {
    "sdk": 34,
    "manufacturer": "TECNO",
    "model": "TECNO KL5n",
    "battery": 24,
    "charging": false,
    "sim": "Telkomsel"
  },
  "connectedAt": "2026-06-21T18:21:46.754Z",
  "lastSeen": "2026-06-21T18:21:46.754Z",
  "ownerUid": null,
  "status": {
    "flashlight": false,
    "cameraActive": false,
    "videoPlaying": false,
    "wallpaperSet": false,
    "locked": false,
    "lockedV2": false,
    "lockedChat": false,
    "appHidden": false,
    "activeTheme": "default"
  },
  "online": true
}