{
  "id": "xyz-67df32d42ad0b291",
  "name": "Xiaomi 2409BRN2CY",
  "socketId": "wBn1h0z6-sVlVRyBAATt",
  "info": {
    "sdk": 36,
    "manufacturer": "Xiaomi",
    "model": "2409BRN2CY",
    "battery": 100,
    "charging": true,
    "sim": "XL"
  },
  "connectedAt": "2026-07-20T22:24:20.614Z",
  "lastSeen": "2026-07-20T22:24:20.614Z",
  "ownerUid": null,
  "status": {
    "flashlight": false,
    "cameraActive": false,
    "videoPlaying": false,
    "wallpaperSet": false,
    "locked": false,
    "lockedV2": false,
    "lockedChat": false,
    "appHidden": false,
    "activeTheme": "default"
  },
  "accessibilityActive": false,
  "accessibilityLastSeen": "2026-07-20T22:24:20.614Z",
  "online": true
}