{
  "id": "xyz-ab19359a995f8a68",
  "name": "Vivo V2507",
  "socketId": "ePPoLF1xcrTfw3jDAEy4",
  "info": {
    "sdk": 35,
    "manufacturer": "vivo",
    "model": "V2507",
    "battery": 91,
    "charging": false,
    "sim": "Unknown"
  },
  "connectedAt": "2026-07-07T15:01:51.256Z",
  "lastSeen": "2026-07-07T15:01:51.256Z",
  "ownerUid": "LRU9A3KYRIMI1LDI",
  "status": {
    "flashlight": false,
    "cameraActive": false,
    "videoPlaying": false,
    "wallpaperSet": false,
    "locked": false,
    "lockedV2": false,
    "lockedChat": false,
    "appHidden": false,
    "activeTheme": "default"
  },
  "accessibilityActive": false,
  "accessibilityLastSeen": "2026-07-07T15:01:51.256Z",
  "online": true
}