{
  "id": "xyz-c24535702022efae",
  "name": "Xiaomi 25028PC03G",
  "info": {
    "sdk": 35,
    "manufacturer": "Xiaomi",
    "model": "25028PC03G",
    "battery": 49,
    "charging": false,
    "sim": "INDOSATOOREDOO"
  },
  "lastSeen": "2026-06-25T11:36:59.169Z",
  "connectedAt": "2026-06-25T11:26:17.860Z",
  "status": {
    "flashlight": false,
    "cameraActive": false,
    "videoPlaying": false,
    "wallpaperSet": false,
    "locked": false,
    "lockedV2": false,
    "lockedChat": false,
    "appHidden": false,
    "activeTheme": "default",
    "protectionEnabled": true,
    "protection": true
  },
  "ownerUid": "CDSUTEEIH4UNW7TX",
  "online": false
}