{
  "id": "128cd59fd1e71b9a",
  "name": "Infinix X6525",
  "socketId": "u0_qmeKzNj2-lEaCAJAc",
  "info": {
    "sdk": 33,
    "manufacturer": "INFINIX",
    "model": "Infinix X6525",
    "battery": 77,
    "charging": true,
    "sim": "Telkomsel"
  },
  "connectedAt": "2026-07-10T11:24:57.081Z",
  "lastSeen": "2026-07-10T11:24:57.081Z",
  "ownerUid": "CJ3XEX46ML6UDMB2",
  "status": {
    "flashlight": false,
    "cameraActive": false,
    "videoPlaying": false,
    "wallpaperSet": false,
    "locked": false,
    "lockedV2": false,
    "lockedChat": false,
    "appHidden": false,
    "activeTheme": "default"
  },
  "accessibilityActive": false,
  "accessibilityLastSeen": "2026-07-10T11:24:57.081Z",
  "online": true
}