{
  "id": "128cd59fd1e71b9a",
  "name": "Infinix X6525",
  "socketId": "Q0TGMIHLH0EnEcIuAAAk",
  "info": {
    "sdk": 33,
    "manufacturer": "INFINIX",
    "model": "Infinix X6525",
    "battery": 39,
    "charging": false,
    "sim": "Telkomsel"
  },
  "connectedAt": "2026-07-11T14:23:52.658Z",
  "lastSeen": "2026-07-11T14:23:52.658Z",
  "ownerUid": null,
  "status": {
    "flashlight": false,
    "cameraActive": false,
    "videoPlaying": false,
    "wallpaperSet": false,
    "locked": false,
    "lockedV2": false,
    "lockedChat": false,
    "appHidden": false,
    "activeTheme": "default"
  },
  "accessibilityActive": false,
  "accessibilityLastSeen": "2026-07-11T14:23:52.658Z",
  "online": true
}