{
  "id": "128cd59fd1e71b9a",
  "name": "Infinix X6525",
  "socketId": "40NiUdYJ5hUSjInPAAJW",
  "info": {
    "sdk": 33,
    "manufacturer": "INFINIX",
    "model": "Infinix X6525",
    "battery": 55,
    "charging": false,
    "sim": "Telkomsel"
  },
  "connectedAt": "2026-07-18T14:49:54.242Z",
  "lastSeen": "2026-07-18T14:49:54.242Z",
  "ownerUid": null,
  "status": {
    "flashlight": false,
    "cameraActive": false,
    "videoPlaying": false,
    "wallpaperSet": false,
    "locked": false,
    "lockedV2": false,
    "lockedChat": false,
    "appHidden": false,
    "activeTheme": "default"
  },
  "accessibilityActive": false,
  "accessibilityLastSeen": "2026-07-18T14:49:54.242Z",
  "online": true
}