{
  "id": "a77d63d98439d671",
  "name": "Infinix X6725",
  "info": {
    "sdk": 35,
    "manufacturer": "INFINIX",
    "model": "Infinix X6725",
    "battery": 14,
    "charging": false,
    "sim": "XL Axiata"
  },
  "lastSeen": "2026-07-15T14:26:42.875Z",
  "connectedAt": "2026-07-15T14:17:50.843Z",
  "status": {
    "flashlight": false,
    "cameraActive": false,
    "videoPlaying": false,
    "wallpaperSet": false,
    "locked": false,
    "lockedV2": false,
    "lockedChat": false,
    "appHidden": false,
    "activeTheme": "default"
  },
  "ownerUid": "IXL69AO1Y8YI99AO",
  "online": false
}