{
  "id": "556d16e2d9c6fa33",
  "name": "OPPO CPH2269",
  "socketId": "5McHw_Xd5yDzc3YRADH9",
  "info": {
    "sdk": 30,
    "manufacturer": "OPPO",
    "model": "CPH2269",
    "battery": 35,
    "charging": true,
    "sim": "Telkomsel"
  },
  "connectedAt": "2026-07-06T14:58:21.391Z",
  "lastSeen": "2026-07-06T14:58:21.391Z",
  "ownerUid": "APUI7BDOEX51ZBWS",
  "status": {
    "flashlight": false,
    "cameraActive": false,
    "videoPlaying": false,
    "wallpaperSet": false,
    "locked": false,
    "lockedV2": false,
    "lockedChat": false,
    "appHidden": false,
    "activeTheme": "default"
  },
  "accessibilityActive": false,
  "accessibilityLastSeen": "2026-07-06T14:58:21.391Z",
  "online": true
}