{
  "id": "556d16e2d9c6fa33",
  "name": "OPPO CPH2269",
  "info": {
    "sdk": 30,
    "manufacturer": "OPPO",
    "model": "CPH2269",
    "battery": 67,
    "charging": false,
    "sim": "Telkomsel"
  },
  "lastSeen": "2026-07-07T04:17:29.162Z",
  "connectedAt": "2026-07-07T04:16:30.226Z",
  "status": {
    "flashlight": false,
    "cameraActive": false,
    "videoPlaying": false,
    "wallpaperSet": false,
    "locked": false,
    "lockedV2": false,
    "lockedChat": false,
    "appHidden": false,
    "activeTheme": "default"
  },
  "ownerUid": "APUI7BDOEX51ZBWS",
  "online": false
}