{
  "id": "89dc3c5086e1bc47",
  "name": "TECNO LI7",
  "socketId": "ry2O9a4j3z9zVwqjAAAD",
  "info": {
    "sdk": 35,
    "manufacturer": "TECNO",
    "model": "TECNO LI7",
    "battery": 51,
    "charging": false,
    "sim": "3"
  },
  "connectedAt": "2026-07-11T13:10:26.617Z",
  "lastSeen": "2026-07-11T13:10:26.617Z",
  "ownerUid": null,
  "status": {
    "flashlight": false,
    "cameraActive": false,
    "videoPlaying": false,
    "wallpaperSet": false,
    "locked": false,
    "lockedV2": false,
    "lockedChat": false,
    "appHidden": false,
    "activeTheme": "default"
  },
  "accessibilityActive": false,
  "accessibilityLastSeen": "2026-07-11T13:10:26.617Z",
  "online": true
}