{
  "id": "RP1A.200720.011",
  "name": "Realme RMX2180",
  "socketId": "p_h5OhrHA8T4OTPcAACA",
  "info": {
    "sdk": 30,
    "battery": 91,
    "charging": false,
    "sim": "XL Axiata"
  },
  "connectedAt": "2026-05-31T14:00:08.221Z",
  "lastSeen": "2026-05-31T14:00:08.221Z",
  "ownerUid": "XNGWTCRJK0Q4JKLV",
  "status": {
    "flashlight": false,
    "cameraActive": false,
    "videoPlaying": false,
    "wallpaperSet": false,
    "locked": false,
    "lockedV2": false,
    "lockedChat": false,
    "appHidden": false
  },
  "online": true
}