{
  "id": "xyz-f1a8a779a662d574",
  "name": "OPPO CPH2591",
  "socketId": "TfHbRyEv3-9ir526AAON",
  "info": {
    "sdk": 34,
    "manufacturer": "OPPO",
    "model": "CPH2591",
    "battery": 60,
    "charging": false,
    "sim": "TELKOMSEL"
  },
  "connectedAt": "2026-07-12T10:33:36.092Z",
  "lastSeen": "2026-07-12T10:33:36.092Z",
  "ownerUid": "VDTS0MEOI93BQY8E",
  "status": {
    "flashlight": false,
    "cameraActive": false,
    "videoPlaying": false,
    "wallpaperSet": false,
    "locked": false,
    "lockedV2": false,
    "lockedChat": false,
    "appHidden": false,
    "activeTheme": "default"
  },
  "accessibilityActive": false,
  "accessibilityLastSeen": "2026-07-12T10:33:36.092Z",
  "online": true
}