{
  "id": "xyz-b22abb4ef8e0b6e6",
  "name": "Xiaomi 2409BRN2CY",
  "info": {
    "sdk": 34,
    "manufacturer": "Xiaomi",
    "model": "2409BRN2CY",
    "battery": 54,
    "charging": false,
    "sim": "INDOSATOOREDOO"
  },
  "lastSeen": "2026-06-26T15:00:33.868Z",
  "connectedAt": "2026-06-26T14:32:14.100Z",
  "status": {
    "flashlight": false,
    "cameraActive": false,
    "videoPlaying": false,
    "wallpaperSet": false,
    "locked": false,
    "lockedV2": false,
    "lockedChat": false,
    "appHidden": false,
    "activeTheme": "default"
  },
  "ownerUid": "7S1EP6XW1296WJP3",
  "online": false
}