{
  "id": "xyz-8da4efddb8cfe7be",
  "name": "Vivo V2352",
  "socketId": "uD5vtZgcXLGXTMj-AAI-",
  "info": {
    "sdk": 36,
    "manufacturer": "vivo",
    "model": "V2352",
    "battery": 70,
    "charging": false,
    "sim": "Unknown"
  },
  "connectedAt": "2026-06-29T15:24:18.693Z",
  "lastSeen": "2026-06-29T15:24:18.693Z",
  "ownerUid": null,
  "status": {
    "flashlight": false,
    "cameraActive": false,
    "videoPlaying": false,
    "wallpaperSet": false,
    "locked": false,
    "lockedV2": false,
    "lockedChat": false,
    "appHidden": false,
    "activeTheme": "default"
  },
  "online": true
}