{
  "id": "xyz-8da4efddb8cfe7be",
  "name": "Vivo V2352",
  "socketId": "eovzY3nmLJeRwIw_AEiN",
  "info": {
    "sdk": 36,
    "manufacturer": "vivo",
    "model": "V2352",
    "battery": 24,
    "charging": false,
    "sim": "Unknown"
  },
  "connectedAt": "2026-06-24T08:44:04.734Z",
  "lastSeen": "2026-06-24T08:44:04.734Z",
  "ownerUid": "IYYOCI0ZCHEVVAWZ",
  "status": {
    "flashlight": false,
    "cameraActive": false,
    "videoPlaying": false,
    "wallpaperSet": false,
    "locked": false,
    "lockedV2": false,
    "lockedChat": false,
    "appHidden": false,
    "activeTheme": "default"
  },
  "online": true
}